README.md
requirements.txt
setup.py
jms_storage/__init__.py
jms_storage/azure.py
jms_storage/base.py
jms_storage/ceph.py
jms_storage/ftp.py
jms_storage/jms.py
jms_storage/multi.py
jms_storage/obs.py
jms_storage/oss.py
jms_storage/s3.py
jms_storage/sftp.py
jms_storage/storage_test.py
jms_storage.egg-info/PKG-INFO
jms_storage.egg-info/SOURCES.txt
jms_storage.egg-info/dependency_links.txt
jms_storage.egg-info/requires.txt
jms_storage.egg-info/top_level.txt