Metadata-Version: 2.1
Name: jms-storage
Version: 0.0.59
Summary: Jumpserver storage python sdk tools
Home-page: http://www.jumpserver.org/
Author: Jumpserver team
Author-email: support@fit2cloud.com
License: MIT Licence
Keywords: jumpserver,storage,oss,s3,elasticsearch
Platform: any
Classifier: Development Status :: 5 - Production/Stable
Classifier: Intended Audience :: Developers
Classifier: License :: OSI Approved :: MIT License
Classifier: Operating System :: OS Independent
Classifier: Programming Language :: Python
Classifier: Programming Language :: Python :: 3.5
Classifier: Programming Language :: Python :: 3.6
